LICENSE
MANIFEST.in
README.md
requirements.txt
setup.py
joker/clients/__init__.py
joker/clients/cas.py
joker/clients/email.py
joker/clients/http.py
joker/clients/monolog.py
joker/clients/namtso.py
joker/clients/printable.py
joker/clients/utils.py
joker_clients.egg-info/PKG-INFO
joker_clients.egg-info/SOURCES.txt
joker_clients.egg-info/dependency_links.txt
joker_clients.egg-info/namespace_packages.txt
joker_clients.egg-info/not-zip-safe
joker_clients.egg-info/requires.txt
joker_clients.egg-info/top_level.txt