Metadata-Version: 2.1
Name: joker-clients
Version: 0.4.3
Summary: simple and reusable client-side toolkits
Home-page: https://github.com/frozflame/joker-clients
Author: frozflame
Author-email: frozflame@outlook.com
License: GNU General Public License (GPL)
Keywords: joker
Classifier: Programming Language :: Python
Classifier: Programming Language :: Python :: 3
Classifier: Programming Language :: Python :: 3.7
Classifier: Programming Language :: Python :: 3.8
Classifier: Programming Language :: Python :: 3.9
Classifier: Programming Language :: Python :: 3.10
Classifier: Programming Language :: Python :: 3.11
Classifier: Programming Language :: Python :: 3.12
Classifier: Programming Language :: Python :: 3.13
Classifier: Programming Language :: Python :: 3.14
Requires-Python: >=3.7
License-File: LICENSE
